{
  "id": "natoko",
  "name": "Natoko",
  "sector": "Spinward Marches",
  "subsector": "D",
  "hex": "3209",
  "uwp": "B582211-8",
  "tradeCodes": [
    "Lo"
  ],
  "allegiance": "Im",
  "bases": [],
  "stellar": {
    "primary": "G2 V",
    "type": "Single"
  },
  "worlds": 7,
  "gasGiants": 3,
  "planetoidBelts": 1,
  "notes": "Good starport. TL8.",
  "wikiUrl": "https://wiki.travellerrpg.com/Natoko_(world)",
  "celestialObjects": [
    {
      "id": "natoko-star",
      "name": "Natoko Primary",
      "type": "Star",
      "orbitAU": 0,
      "bearing": 0,
      "radiusKm": 696340,
      "stellarClass": "G2 V",
      "stellarInfo": {
        "temperature": "5,200-6,000 K",
        "luminosity": "0.6-1.5 Solar",
        "mass": "0.8-1.04 Solar",
        "habitableZone": "0.8-1.2 AU",
        "description": "Yellow main sequence (Sol-like)"
      },
      "transponder": "NONE",
      "gmNotes": "G2 V primary.",
      "cameraSettings": {
        "zoomMultiplier": 0.15,
        "offsetX": 0.25,
        "offsetY": 0.1,
        "description": "Wide corona view with inner system visible"
      }
    },
    {
      "id": "natoko-mainworld",
      "name": "Natoko",
      "type": "Planet",
      "orbitAU": 1.2372013217078983,
      "bearing": 266,
      "radiusKm": 4800,
      "uwp": "B582211-8",
      "atmosphere": "Dense",
      "breathable": true,
      "inGoldilocks": true,
      "transponder": "NATOKO CONTROL",
      "gmNotes": "Mainworld. Pop 10^2. TL8.",
      "cameraSettings": {
        "zoomMultiplier": 0.8,
        "offsetX": 0,
        "offsetY": 0,
        "description": "Standard world view"
      }
    },
    {
      "id": "natoko-highport",
      "name": "Natoko Highport",
      "type": "Highport",
      "parent": "natoko-mainworld",
      "orbitKm": 400,
      "bearing": 268,
      "radiusKm": 2,
      "transponder": "NATOKO HIGHPORT",
      "gmNotes": "Class B Good starport orbital facility.",
      "celestial": false,
      "cameraSettings": {
        "zoomMultiplier": 1,
        "offsetX": 0,
        "offsetY": 0,
        "description": "Station approach"
      }
    },
    {
      "id": "natoko-gasgiant",
      "name": "Natoko Gas Giant",
      "type": "Gas Giant",
      "orbitAU": 5.5808142404428756,
      "bearing": 136,
      "radiusKm": 68341.61931696747,
      "transponder": "NONE",
      "gmNotes": "Gas giant suitable for fuel skimming.",
      "cameraSettings": {
        "zoomMultiplier": 0.5,
        "offsetX": 0,
        "offsetY": 0,
        "description": "Gas giant view"
      }
    }
  ],
  "locations": {
    "default": "natoko-mainworld",
    "starport": "natoko-highport",
    "orbit": "natoko-mainworld"
  }
}